ipmlab/__init__.py
ipmlab/__main__.py
ipmlab/aaru.py
ipmlab/config.py
ipmlab/configure.py
ipmlab/configure_linux.py
ipmlab/configure_windows.py
ipmlab/ddrescue.py
ipmlab/dfxml.py
ipmlab/fiwalk.py
ipmlab/ipmlab.py
ipmlab/mdo.py
ipmlab/pmworker.py
ipmlab/conf/config-linux.xml
ipmlab/conf/config-win.xml
ipmlab/icons/ipmlab.png
ipmlab/kbapi/__init__.py
ipmlab/kbapi/sru.py
ipmlab/socketserver/__init__.py
ipmlab/socketserver/server.py
ipmlab-0.3.0.dist-info/LICENSE
ipmlab-0.3.0.dist-info/METADATA
ipmlab-0.3.0.dist-info/WHEEL
ipmlab-0.3.0.dist-info/entry_points.txt
ipmlab-0.3.0.dist-info/top_level.txt
ipmlab-0.3.0.dist-info/RECORD
